fsm-assignments/problem1_seqdet/seq_detect_mealy.v

`timescale 1ns/1ps

module seq_detect_mealy(
    input  wire clk,
    input  wire rst,   // synchronous active-high
    input  wire din,   // serial input bit per clock
    output reg  y      // 1-cycle pulse when pattern ...1101 seen
);

    
    localparam S0   = 2'd0;
    localparam S1   = 2'd1;
    localparam S11  = 2'd2;
    localparam S110 = 2'd3;

    reg [1:0] state, next_state;

    // Next-state and Mealy output
    always @* begin
        next_state = state;
        y = 1'b0;

        case (state)
            S0: begin
                // matched nothing so far
                if (din) next_state = S1;     // saw '1'
                else     next_state = S0;     // stay
            end

            S1: begin
                // matched "1"
                if (din) next_state = S11;    // saw '11'
                else     next_state = S0;     // '10' -> no prefix match
            end

            S11: begin
                // matched "11"
                if (din) next_state = S11;    // '111' -> suffix '11' holds
                else     next_state = S110;   // '110'
            end

            S110: begin
                // matched "110"
                if (din) begin
                    // complete "1101" -> pulse now; fallback to longest prefix "1"
                    y = 1'b1;
                    next_state = S1;
                end else begin
                    // '1100' -> no prefix
                    next_state = S0;
                end
            end

            default: begin
                next_state = S0;
            end
        endcase
    end

    // State register with synchronous, active-high reset
    always @(posedge clk) begin
        if (rst) state <= S0;
        else     state <= next_state;
    end

endmodule

fsm-assignments/problem1_seqdet/tb_seq_detect_mealy.v
// problem1_seqdet/tb_seq_detect_mealy.v
// Testbench for Mealy sequence detector (pattern 1101 with overlap).
`timescale 1ns/1ps

module tb_seq_detect_mealy;
    reg  clk, rst, din;
    wire y;

    // DUT
    seq_detect_mealy dut(.clk(clk), .rst(rst), .din(din), .y(y));

    // Clock: 10 ns period (100 MHz)
    initial begin
        clk = 0;
        forever #5 clk = ~clk;
    end

    // Test sequence
    integer i;
    integer n;          // <<-- moved here
    reg [0:99] stream;  // up to 100 bits if needed; index grows to the right

    task drive_stream(input integer nbits);
        begin
            for (i = 0; i < nbits; i = i + 1) begin
                din = stream[i];
                @(posedge clk);
                // Log cycle, input, and y pulse
                $display("t=%0t ns  cycle=%0d  din=%0d  y=%0d", $time, i, din, y);
            end
        end
    endtask

    initial begin
        // Wave dump
        $dumpfile("waves/dump.vcd");
        $dumpvars(0, tb_seq_detect_mealy);

        // Reset
        rst = 1;
        din = 0;
        repeat (2) @(posedge clk);
        rst = 0;

        // STREAM-1: demonstrates overlaps; bits: 1101101101
        // Expected pulse indices (0-based): 3, 6, 9
        stream[0] = 1;
        stream[1] = 1;
        stream[2] = 0;
        stream[3] = 1;  // pulse
        stream[4] = 1;
        stream[5] = 0;
        stream[6] = 1;  // pulse
        stream[7] = 1;
        stream[8] = 0;
        stream[9] = 1;  // pulse
        drive_stream(10);

        // Small reset between streams
        rst = 1; @(posedge clk); rst = 0;

        // STREAM-2: random bits with some hits
        // Sequence chosen: 1 0 1 1 0 1 1 0 0 1 1 0 1
        // Expected pulse indices (0-based): 6, 12
        n = 13;
        stream[0]  = 1;
        stream[1]  = 0;
        stream[2]  = 1;
        stream[3]  = 1;
        stream[4]  = 0;
        stream[5]  = 1;
        stream[6]  = 1;   // pulse
        stream[7]  = 0;
        stream[8]  = 0;
        stream[9]  = 1;
        stream[10] = 1;
        stream[11] = 0;
        stream[12] = 1;   // pulse
        drive_stream(n);

        // Finish
        @(posedge clk);
        $finish;
    end
endmodule

fsm-assignments/problem1_seqdet/waves/dump.vcd
$date
	Tue Aug 19 13:19:07 2025
$end
$version
	Icarus Verilog
$end
$timescale
	1ps
$end
$scope module tb_seq_detect_mealy $end
$var wire 1 ! y $end
$var reg 1 " clk $end
$var reg 1 # din $end
$var reg 1 $ rst $end
$var reg 100 % stream [0:99] $end
$var integer 32 & i [31:0] $end
$var integer 32 ' n [31:0] $end
$scope module dut $end
$var wire 1 " clk $end
$var wire 1 # din $end
$var wire 1 $ rst $end
$var parameter 2 ( S0 $end
$var parameter 2 ) S1 $end
$var parameter 2 * S11 $end
$var parameter 2 + S110 $end
$var reg 2 , next_state [1:0] $end
$var reg 2 - state [1:0] $end
$var reg 1 ! y $end
$upscope $end
$scope task drive_stream $end
$var integer 32 . nbits [31:0] $end
$upscope $end
$upscope $end
$enddefinitions $end
$comment Show the parameter values. $end
$dumpall
b11 +
b10 *
b1 )
b0 (
$end
#0
$dumpvars
bx .
bx -
b0 ,
bx '
bx &
bx %
1$
0#
0"
0!
$end
#5000
b0 -
1"
#10000
0"
#15000
b1 ,
1#
b0 &
b1010 .
b1101101101xxxxxxxxxxxxxxxxxxxxxxxxxxxxxxxxxxxxxxxxxxxxxxxxxxxxxxxxxxxxxxxxxxxxxxxxxxxxxxxxxxxxxxxxxx %
0$
1"
#20000
0"
#25000
b10 ,
b1 -
b1 &
1"
#30000
0"
#35000
b10 -
b11 ,
0#
b10 &
1"
#40000
0"
#45000
1!
b11 -
b1 ,
1#
b11 &
1"
#50000
0"
#55000
b10 ,
0!
b1 -
b100 &
1"
#60000
0"
#65000
b10 -
b11 ,
0#
b101 &
1"
#70000
0"
#75000
1!
b11 -
b1 ,
1#
b110 &
1"
#80000
0"
#85000
b10 ,
0!
b1 -
b111 &
1"
#90000
0"
#95000
b10 -
b11 ,
0#
b1000 &
1"
#100000
0"
#105000
1!
b11 -
b1 ,
1#
b1001 &
1"
#110000
0"
#115000
b10 ,
0!
b1 -
1$
b1010 &
1"
#120000
0"
#125000
b10 -
b0 &
b1101 .
b1011011001101xxxxxxxxxxxxxxxxxxxxxxxxxxxxxxxxxxxxxxxxxxxxxxxxxxxxxxxxxxxxxxxxxxxxxxxxxxxxxxxxxxxxxxx %
b1101 '
0$
1"
#130000
0"
#135000
b11 ,
0#
b1 &
1"
#140000
0"
#145000
1!
b11 -
b1 ,
1#
b10 &
1"
#150000
0"
#155000
b10 ,
0!
b1 -
b11 &
1"
#160000
0"
#165000
b10 -
b11 ,
0#
b100 &
1"
#170000
0"
#175000
1!
b11 -
b1 ,
1#
b101 &
1"
#180000
0"
#185000
b10 ,
0!
b1 -
b110 &
1"
#190000
0"
#195000
b10 -
b11 ,
0#
b111 &
1"
#200000
0"
#205000
b0 ,
b11 -
b1000 &
1"
#210000
0"
#215000
b0 -
0!
b1 ,
1#
b1001 &
1"
#220000
0"
#225000
b10 ,
b1 -
b1010 &
1"
#230000
0"
#235000
b10 -
b11 ,
0#
b1011 &
1"
#240000
0"
#245000
1!
b11 -
b1 ,
1#
b1100 &
1"
#250000
0"
#255000
b10 ,
0!
b1 -
b1101 &
1"
#260000
0"
#265000
b10 -
1"
