fsm-assignments/problem3_vending/vending_mealy.v
module vending_mealy(
    input  wire       clk,
    input  wire       rst,       // sync active-high reset
    input  wire [1:0] coin,      // 01=5, 10=10, 00=idle, ignore 11
    output reg        dispense,  // 1-cycle pulse
    output reg        chg5       // 1-cycle pulse when returning 5
);

    // State encoding (Verilog-2001 style)
    parameter S0  = 2'b00;  // total = 0
    parameter S5  = 2'b01;  // total = 5
    parameter S10 = 2'b10;  // total = 10
    parameter S15 = 2'b11;  // total = 15

    reg [1:0] state, next_state;

    // Next state logic + outputs (Mealy machine)
    always @(*) begin
        next_state = state;
        dispense   = 0;
        chg5       = 0;

        case (state)
            S0: begin
                if (coin == 2'b01) next_state = S5;       // +5
                else if (coin == 2'b10) next_state = S10; // +10
            end

            S5: begin
                if (coin == 2'b01) next_state = S10;      // +5
                else if (coin == 2'b10) next_state = S15; // +10
            end

            S10: begin
                if (coin == 2'b01) next_state = S15;      // +5
                else if (coin == 2'b10) begin             // total = 20
                    dispense   = 1;
                    next_state = S0;                      // reset after vend
                end
            end

            S15: begin
                if (coin == 2'b01) begin                  // total = 20
                    dispense   = 1;
                    next_state = S0;
                end
                else if (coin == 2'b10) begin             // total = 25
                    dispense   = 1;
                    chg5       = 1;
                    next_state = S0;
                end
            end
        endcase
    end

    // State register (synchronous reset)
    always @(posedge clk) begin
        if (rst)
            state <= S0;
        else
            state <= next_state;
    end

endmodule

fsm-assignments/problem3_vending/tb_vending_mealy.v
`timescale 1ns/1ps
module tb_vending_mealy;
    reg clk, rst;
    reg [1:0] coin;
    wire dispense, chg5;

    // DUT instantiation
    vending_mealy dut (
        .clk(clk), .rst(rst), .coin(coin),
        .dispense(dispense), .chg5(chg5)
    );

    // Clock generation (10ns period)
    initial begin
        clk = 0;
        forever #5 clk = ~clk;
    end

    // Stimulus
    initial begin
        $dumpfile("waves/dump.vcd");
        $dumpvars(0, tb_vending_mealy);

        // Reset
        rst = 1; coin = 2'b00;
        #12;
        rst = 0;

        // Case 1: 10 + 10 = vend
        coin = 2'b10; #10; coin = 2'b00; #10;
        coin = 2'b10; #10; coin = 2'b00; #10;

        // Case 2: 5 + 5 + 10 = vend
        coin = 2'b01; #10; coin = 2'b00; #10;
        coin = 2'b01; #10; coin = 2'b00; #10;
        coin = 2'b10; #10; coin = 2'b00; #10;

        // Case 3: 10 + 10 + 5 = vend + chg5
        coin = 2'b10; #10; coin = 2'b00; #10;
        coin = 2'b10; #10; coin = 2'b00; #10;
        coin = 2'b01; #10; coin = 2'b00; #10;

        #50 $finish;
    end
endmodule

fsm-assignments/problem3_vending/waves/dump.vcd
$date
	Tue Aug 19 15:49:55 2025
$end
$version
	Icarus Verilog
$end
$timescale
	1ps
$end
$scope module tb_vending_mealy $end
$var wire 1 ! dispense $end
$var wire 1 " chg5 $end
$var reg 1 # clk $end
$var reg 2 $ coin [1:0] $end
$var reg 1 % rst $end
$scope module dut $end
$var wire 1 # clk $end
$var wire 2 & coin [1:0] $end
$var wire 1 % rst $end
$var parameter 2 ' S0 $end
$var parameter 2 ( S10 $end
$var parameter 2 ) S15 $end
$var parameter 2 * S5 $end
$var reg 1 " chg5 $end
$var reg 1 ! dispense $end
$var reg 2 + next_state [1:0] $end
$var reg 2 , state [1:0] $end
$upscope $end
$upscope $end
$enddefinitions $end
$comment Show the parameter values. $end
$dumpall
b1 *
b11 )
b10 (
b0 '
$end
#0
$dumpvars
bx ,
bx +
b0 &
1%
b0 $
0#
0"
0!
$end
#5000
b0 +
b0 ,
1#
#10000
0#
#12000
b10 +
b10 $
b10 &
0%
#15000
b0 +
1!
b10 ,
1#
#20000
0#
#22000
0!
b10 +
b0 $
b0 &
#25000
1#
#30000
0#
#32000
b0 +
1!
b10 $
b10 &
#35000
b10 +
0!
b0 ,
1#
#40000
0#
#42000
b0 +
b0 $
b0 &
#45000
1#
#50000
0#
#52000
b1 +
b1 $
b1 &
#55000
b10 +
b1 ,
1#
#60000
0#
#62000
b1 +
b0 $
b0 &
#65000
1#
#70000
0#
#72000
b10 +
b1 $
b1 &
#75000
b11 +
b10 ,
1#
#80000
0#
#82000
b10 +
b0 $
b0 &
#85000
1#
#90000
0#
#92000
b0 +
1!
b10 $
b10 &
#95000
b10 +
0!
b0 ,
1#
#100000
0#
#102000
b0 +
b0 $
b0 &
#105000
1#
#110000
0#
#112000
b10 +
b10 $
b10 &
#115000
b0 +
1!
b10 ,
1#
#120000
0#
#122000
0!
b10 +
b0 $
b0 &
#125000
1#
#130000
0#
#132000
b0 +
1!
b10 $
b10 &
#135000
b10 +
0!
b0 ,
1#
#140000
0#
#142000
b0 +
b0 $
b0 &
#145000
1#
#150000
0#
#152000
b1 +
b1 $
b1 &
#155000
b10 +
b1 ,
1#
#160000
0#
#162000
b1 +
b0 $
b0 &
