fsm-assignments/problem4_link/slave_fsm.v
module slave_fsm(
    input  wire       clk,
    input  wire       rst,   // synchronous reset
    input  wire       req,
    input  wire [7:0] data_in,
    output reg        ack,
    output reg [7:0]  last_byte
);

    reg [2:0] state;
    reg [1:0] hold_cnt;

    localparam IDLE   = 3'd0,
               LATCH  = 3'd1,
               HOLD   = 3'd2,
               DROP   = 3'd3;

    always @(posedge clk) begin
        if (rst) begin
            state     <= IDLE;
            ack       <= 0;
            last_byte <= 0;
            hold_cnt  <= 0;
        end else begin
            case(state)
                IDLE: begin
                    ack <= 0;
                    if (req) begin
                        last_byte <= data_in; // latch data
                        ack       <= 1;
                        hold_cnt  <= 2;
                        state     <= HOLD;
                    end
                end

                HOLD: begin
                    if (hold_cnt > 1) begin
                        hold_cnt <= hold_cnt - 1;
                    end else begin
                        state <= DROP;
                    end
                end

                DROP: begin
                    ack   <= 0;
                    if (!req) state <= IDLE;
                end
            endcase
        end
    end
endmodule

fsm-assignments/problem4_link/master_fsm.v
module master_fsm(
    input  wire       clk,
    input  wire       rst,   // synchronous reset
    input  wire       ack,
    output reg        req,
    output reg [7:0]  data,
    output reg        done   // 1-cycle when burst completes
);

    // Example data burst: A0..A3
    reg [7:0] burst [0:3];
    initial begin
        burst[0] = 8'hA0;
        burst[1] = 8'hA1;
        burst[2] = 8'hA2;
        burst[3] = 8'hA3;
    end

    reg [2:0] state;
    reg [1:0] index;

    localparam IDLE  = 3'd0,
               SEND  = 3'd1,
               WAIT_ACK = 3'd2,
               DROP_REQ = 3'd3,
               NEXT  = 3'd4,
               DONE  = 3'd5;

    always @(posedge clk) begin
        if (rst) begin
            state <= IDLE;
            req   <= 0;
            data  <= 0;
            index <= 0;
            done  <= 0;
        end else begin
            done <= 0; // default
            case(state)
                IDLE: begin
                    index <= 0;
                    req   <= 0;
                    state <= SEND;
                end

                SEND: begin
                    data  <= burst[index];
                    req   <= 1;
                    state <= WAIT_ACK;
                end

                WAIT_ACK: begin
                    if (ack) state <= DROP_REQ;
                end

                DROP_REQ: begin
                    req   <= 0;
                    state <= NEXT;
                end

                NEXT: begin
                    if (index == 2'd3) begin
                        state <= DONE;
                    end else begin
                        index <= index + 1;
                        state <= SEND;
                    end
                end

                DONE: begin
                    done  <= 1;
                    state <= IDLE;
                end
            endcase
        end
    end
endmodule

fsm-assignments/problem4_link/link_top.v
module link_top(
    input  wire clk,
    input  wire rst,
    output wire done
);
    wire req, ack;
    wire [7:0] data, last_byte;

    master_fsm u_master(
        .clk(clk), .rst(rst),
        .ack(ack), .req(req), .data(data), .done(done)
    );

    slave_fsm u_slave(
        .clk(clk), .rst(rst),
        .req(req), .data_in(data), .ack(ack), .last_byte(last_byte)
    );
endmodule

fsm-assignments/problem4_link/tb_link_top.v
`timescale 1ns/1ps
module tb_link_top;

    reg clk, rst;
    wire done;

    link_top dut(.clk(clk), .rst(rst), .done(done));

    // Clock generation
    initial clk = 0;
    always #5 clk = ~clk;  // 100 MHz clock

    // Reset + Stimulus
    initial begin
        $dumpfile("dump.vcd");
        $dumpvars(0, tb_link_top);

        rst = 1;
        #15 rst = 0;

        wait(done);
        #20;
        $finish;
    end

endmodule

fsm-assignments/problem4_link/dump.vcd
$date
	Tue Aug 19 22:12:26 2025
$end
$version
	Icarus Verilog
$end
$timescale
	1ps
$end
$scope module tb_link_top $end
$var wire 1 ! done $end
$var reg 1 " clk $end
$var reg 1 # rst $end
$scope module dut $end
$var wire 1 " clk $end
$var wire 1 # rst $end
$var wire 1 $ req $end
$var wire 8 % last_byte [7:0] $end
$var wire 1 ! done $end
$var wire 8 & data [7:0] $end
$var wire 1 ' ack $end
$scope module u_master $end
$var wire 1 " clk $end
$var wire 1 # rst $end
$var wire 1 ' ack $end
$var parameter 3 ( DONE $end
$var parameter 3 ) DROP_REQ $end
$var parameter 3 * IDLE $end
$var parameter 3 + NEXT $end
$var parameter 3 , SEND $end
$var parameter 3 - WAIT_ACK $end
$var reg 8 . data [7:0] $end
$var reg 1 ! done $end
$var reg 2 / index [1:0] $end
$var reg 1 $ req $end
$var reg 3 0 state [2:0] $end
$upscope $end
$scope module u_slave $end
$var wire 1 " clk $end
$var wire 8 1 data_in [7:0] $end
$var wire 1 $ req $end
$var wire 1 # rst $end
$var parameter 3 2 DROP $end
$var parameter 3 3 HOLD $end
$var parameter 3 4 IDLE $end
$var parameter 3 5 LATCH $end
$var reg 1 ' ack $end
$var reg 2 6 hold_cnt [1:0] $end
$var reg 8 7 last_byte [7:0] $end
$var reg 3 8 state [2:0] $end
$upscope $end
$upscope $end
$upscope $end
$enddefinitions $end
$comment Show the parameter values. $end
$dumpall
b1 5
b0 4
b10 3
b11 2
b10 -
b1 ,
b100 +
b0 *
b11 )
b101 (
$end
#0
$dumpvars
bx 8
bx 7
bx 6
bx 1
bx 0
bx /
bx .
x'
bx &
bx %
x$
1#
0"
x!
$end
#5000
0!
b0 /
b0 &
b0 .
b0 1
0$
b0 0
b0 6
b0 %
b0 7
0'
b0 8
1"
#10000
0"
#15000
b1 0
1"
0#
#20000
0"
#25000
b10 0
1$
b10100000 &
b10100000 .
b10100000 1
1"
#30000
0"
#35000
b10 8
b10 6
1'
b10100000 %
b10100000 7
1"
#40000
0"
#45000
b11 0
b1 6
1"
#50000
0"
#55000
b11 8
b100 0
0$
1"
#60000
0"
#65000
b1 0
b1 /
b0 8
0'
1"
#70000
0"
#75000
b10 0
1$
b10100001 &
b10100001 .
b10100001 1
1"
#80000
0"
#85000
b10 8
b10 6
1'
b10100001 %
b10100001 7
1"
#90000
0"
#95000
b1 6
b11 0
1"
#100000
0"
#105000
b100 0
0$
b11 8
1"
#110000
0"
#115000
b0 8
0'
b1 0
b10 /
1"
#120000
0"
#125000
b10 0
1$
b10100010 &
b10100010 .
b10100010 1
1"
#130000
0"
#135000
b10 8
b10 6
1'
b10100010 %
b10100010 7
1"
#140000
0"
#145000
b11 0
b1 6
1"
#150000
0"
#155000
b11 8
b100 0
0$
1"
#160000
0"
#165000
b1 0
b11 /
b0 8
0'
1"
#170000
0"
#175000
b10 0
1$
b10100011 &
b10100011 .
b10100011 1
1"
#180000
0"
#185000
b10 8
b10 6
1'
b10100011 %
b10100011 7
1"
#190000
0"
#195000
b1 6
b11 0
1"
#200000
0"
#205000
b100 0
0$
b11 8
1"
#210000
0"
#215000
b0 8
0'
b101 0
1"
#220000
0"
#225000
b0 0
1!
1"
#230000
0"
#235000
b1 0
b0 /
0!
1"
#240000
0"
#245000
b10 0
1$
b10100000 &
b10100000 .
b10100000 1
1"
